bima-0.2.3.dist-info/METADATA
bima-0.2.3.dist-info/WHEEL
bima-0.2.3.dist-info/licenses/LICENSE
bima/__init__.py
bima/_bima.cpython-312-darwin.so
bima/core.py
bima/initial.py
bima/method/__init__.py
bima/method/close_encounter.py
bima/method/force.py
bima/method/solve.py
bima/method/timestep.py
bima/simulation.py
bima-0.2.3.dist-info/RECORD
