Metadata-Version: 2.4
Name: bima
Version: 0.2.3
Classifier: Programming Language :: Rust
Classifier: Programming Language :: Python :: Implementation :: CPython
Classifier: Programming Language :: Python :: Implementation :: PyPy
Requires-Dist: numpy>=2.3.4
Requires-Dist: matplotlib ; extra == 'dev'
Requires-Dist: jupyterlab ; extra == 'dev'
Requires-Dist: maturin>=1.10,<2.0 ; extra == 'dev'
Provides-Extra: dev
License-File: LICENSE
Summary: N-body simulation powered with Rust backend
Author-email: Muhammad Ali Syaifudin <muhammad.ali.syaifudin@hotmail.com>
Requires-Python: >=3.12
